slack_deferred_aws.py
slack_deferred_gcp.py
slack_messaging.py
slack_serverless.py
slack_serverless-2024.1018.dist-info/LICENSE.md
slack_serverless-2024.1018.dist-info/METADATA
slack_serverless-2024.1018.dist-info/WHEEL
slack_serverless-2024.1018.dist-info/top_level.txt
slack_serverless-2024.1018.dist-info/RECORD
