Metadata-Version: 2.1
Name: slack-serverless
Version: 2024.1018
Summary: Simplified serverless Slack bot interactions
Author-email: Ross Bamford <roscopeco@gmail.com>
License: Copyright 2023 Ross Bamford & Contributors
Project-URL: Homepage, https://github.com/roscopeco/slack-serverless
Keywords: slack,serverless,cloud,chatbot
Classifier: License :: OSI Approved :: MIT License
Classifier: Programming Language :: Python
Classifier: Programming Language :: Python :: 3
Requires-Python: >=3.10
License-File: LICENSE.md
Requires-Dist: requests >=2.32.0
Provides-Extra: dev
Requires-Dist: black ; extra == 'dev'
Requires-Dist: bumpver ; extra == 'dev'
Requires-Dist: pre-commit ; extra == 'dev'
Requires-Dist: isort ; extra == 'dev'
Requires-Dist: pip-tools ; extra == 'dev'
Requires-Dist: pytest ; extra == 'dev'
Requires-Dist: sure ; extra == 'dev'
Requires-Dist: httpretty ; extra == 'dev'
